examples/__init__.py
examples/titanic.py
handyspark/__init__.py
handyspark/plot.py
handyspark/stats.py
handyspark/util.py
handyspark/extensions/__init__.py
handyspark/extensions/common.py
handyspark/extensions/evaluation.py
handyspark/extensions/types.py
handyspark/ml/__init__.py
handyspark/ml/base.py
handyspark/sql/__init__.py
handyspark/sql/dataframe.py
handyspark/sql/datetime.py
handyspark/sql/pandas.py
handyspark/sql/schema.py
handyspark/sql/string.py
handyspark/sql/transform.py
handyspark-0.2.1a1.dist-info/DESCRIPTION.rst
handyspark-0.2.1a1.dist-info/METADATA
handyspark-0.2.1a1.dist-info/RECORD
handyspark-0.2.1a1.dist-info/WHEEL
handyspark-0.2.1a1.dist-info/metadata.json
handyspark-0.2.1a1.dist-info/top_level.txt
