Metadata-Version: 2.0
Name: handyspark
Version: 0.2.1a1
Summary: HandySpark - bringing pandas-like capabilities to Spark dataframes
Home-page: https://github.com/dvgodoy/handyspark
Author: Daniel Voigt Godoy
Author-email: datagnosis@gmail.com
License: MIT
Keywords: spark,big data,data cleaning,visualization,exploratory data analysis,pandas
Platform: UNKNOWN
Classifier: Development Status :: 3 - Alpha
Classifier: Intended Audience :: Developers
Classifier: Intended Audience :: Education
Classifier: Intended Audience :: Science/Research
Classifier: Topic :: Scientific/Engineering
Classifier: Topic :: Scientific/Engineering :: Artificial Intelligence
Classifier: Topic :: Scientific/Engineering :: Visualization
Classifier: Topic :: System :: Distributed Computing
Classifier: License :: OSI Approved :: MIT License
Classifier: Programming Language :: Python :: 3
Requires-Dist: pyspark
Requires-Dist: matplotlib
Requires-Dist: numpy
Requires-Dist: scipy
Requires-Dist: seaborn
Requires-Dist: pandas
Requires-Dist: scikit-learn
Requires-Dist: findspark
Requires-Dist: pyarrow
